{
  "assets": [
    {
      "id": "image_0",
      "w": 441,
      "h": 464,
      "u": "images/",
      "p": "img_0.png",
      "e": 0
    },
    {
      "id": "image_1",
      "w": 484,
      "h": 489,
      "u": "images/",
      "p": "img_1.png",
      "e": 0
    },
    {
      "id": "image_2",
      "w": 481,
      "h": 488,
      "u": "images/",
      "p": "img_2.png",
      "e": 0
    },
    {
      "id": "image_3",
      "w": 565,
      "h": 493,
      "u": "images/",
      "p": "img_3.png",
      "e": 0
    },
    {
      "id": "image_4",
      "w": 490,
      "h": 370,
      "u": "images/",
      "p": "img_4.png",
      "e": 0
    }
  ],
  "chars": [
    {
      "ch": "M",
      "size": 36,
      "style": "Regular",
      "w": 88.92,
      "data": {
        "shapes": [
          {
            "ty": "gr",
            "it": [
              {
                "ind": 0,
                "ty": "sh",
                "ix": 1,
                "ks": {
                  "a": 0,
                  "k": {
                    "i": [
                      [
                        0,
                        0
                      ],
                      [
                        0,
                        0
                      ],
                      [
                        0,
                        0
                      ],
                      [
                        0.716,
                        -1.041
                      ],
                      [
                        2.832,
                        0
                      ],
                      [
                        0,
                        0
                      ],
                      [
                        0,
                        0
                      ],
                      [
                        0,
                        0
                      ],
                      [
                        0,
                        0
                      ],
                      [
                        0,
                        0
                      ],
                      [
                        1.204,
                        1.367
                      ],
                      [
                        0,
                        4.07
                      ],
                      [
                        0,
                        0
                      ],
                      [
                        -0.716,
                        1.042
                      ],
                      [
                        -2.832,
                        0
                      ],
                      [
                        0,
                        0
                      ],
                      [
                        0,
                        0
                      ],
                      [
                        0,
                        0
                      ],
                      [
                        0,
                        0
                      ],
                      [
                        0,
                        0
                      ],
                      [
                        0,
                        0
                      ],
                      [
                        0,
                        0
                      ],
                      [
                        -1.221,
                        -0.635
                      ],
                      [
                        -0.456,
                        -0.944
                      ],
                      [
                        0,
                        -2.93
                      ],
                      [
                        0,
                        0
                      ],
                      [
                        0.716,
                        -1.041
                      ],
                      [
                        2.799,
                        0
                      ],
                      [
                        0,
                        0
                      ],
                      [
                        0,
                        0
                      ],
                      [
                        0,
                        0
                      ],
                      [
                        0,
                        0
                      ],
                      [
                        0,
                        0
                      ],
                      [
                        1.204,
                        1.367
                      ],
                      [
                        0,
                        4.07
                      ],
                      [
                        0,
                        0
                      ],
                      [
                        0,
                        0
                      ]
                    ],
                    "o": [
                      [
                        0,
                        0
                      ],
                      [
                        0,
                        0
                      ],
                      [
                        0,
                        3.711
                      ],
                      [
                        -1.14,
                        1.693
                      ],
                      [
                        0,
                        0
                      ],
                      [
                        0,
                        0
                      ],
                      [
                        0,
                        0
                      ],
                      [
                        0,
                        0
                      ],
                      [
                        0,
                        0
                      ],
                      [
                        -2.605,
                        0
                      ],
                      [
                        -0.912,
                        -1.009
                      ],
                      [
                        0,
                        0
                      ],
                      [
                        0,
                        -3.711
                      ],
                      [
                        1.172,
                        -1.692
                      ],
                      [
                        0,
                        0
                      ],
                      [
                        0,
                        0
                      ],
                      [
                        0,
                        0
                      ],
                      [
                        0,
                        0
                      ],
                      [
                        0,
                        0
                      ],
                      [
                        0,
                        0
                      ],
                      [
                        0,
                        0
                      ],
                      [
                        2.702,
                        0
                      ],
                      [
                        1.221,
                        0.635
                      ],
                      [
                        0.651,
                        1.302
                      ],
                      [
                        0,
                        0
                      ],
                      [
                        0,
                        3.711
                      ],
                      [
                        -1.172,
                        1.693
                      ],
                      [
                        0,
                        0
                      ],
                      [
                        0,
                        0
                      ],
                      [
                        0,
                        0
                      ],
                      [
                        0,
                        0
                      ],
                      [
                        0,
                        0
                      ],
                      [
                        -2.605,
                        0
                      ],
                      [
                        -0.879,
                        -1.009
                      ],
                      [
                        0,
                        0
                      ],
                      [
                        0,
                        0
                      ],
                      [
                        0,
                        0
                      ]
                    ],
                    "v": [
                      [
                        42.529,
                        0
                      ],
                      [
                        68.066,
                        -55.713
                      ],
                      [
                        68.066,
                        -11.475
                      ],
                      [
                        66.992,
                        -4.346
                      ],
                      [
                        61.035,
                        -1.807
                      ],
                      [
                        58.691,
                        -1.807
                      ],
                      [
                        58.691,
                        0
                      ],
                      [
                        86.816,
                        0
                      ],
                      [
                        86.816,
                        -1.807
                      ],
                      [
                        84.521,
                        -1.807
                      ],
                      [
                        78.809,
                        -3.857
                      ],
                      [
                        77.441,
                        -11.475
                      ],
                      [
                        77.441,
                        -54.736
                      ],
                      [
                        78.516,
                        -61.865
                      ],
                      [
                        84.521,
                        -64.404
                      ],
                      [
                        86.816,
                        -64.404
                      ],
                      [
                        86.816,
                        -66.211
                      ],
                      [
                        68.066,
                        -66.211
                      ],
                      [
                        44.434,
                        -14.404
                      ],
                      [
                        20.41,
                        -66.211
                      ],
                      [
                        1.66,
                        -66.211
                      ],
                      [
                        1.66,
                        -64.404
                      ],
                      [
                        7.544,
                        -63.452
                      ],
                      [
                        10.059,
                        -61.084
                      ],
                      [
                        11.035,
                        -54.736
                      ],
                      [
                        11.035,
                        -11.475
                      ],
                      [
                        9.961,
                        -4.346
                      ],
                      [
                        4.004,
                        -1.807
                      ],
                      [
                        1.66,
                        -1.807
                      ],
                      [
                        1.66,
                        0
                      ],
                      [
                        24.707,
                        0
                      ],
                      [
                        24.707,
                        -1.807
                      ],
                      [
                        22.363,
                        -1.807
                      ],
                      [
                        16.65,
                        -3.857
                      ],
                      [
                        15.332,
                        -11.475
                      ],
                      [
                        15.332,
                        -55.713
                      ],
                      [
                        40.918,
                        0
                      ]
                    ],
                    "c": true
                  },
                  "ix": 2
                },
                "nm": "M",
                "mn": "ADBE Vector Shape - Group",
                "hd": false
              }
            ],
            "nm": "M",
            "np": 3,
            "cix": 2,
            "bm": 0,
            "ix": 1,
            "mn": "ADBE Vector Group",
            "hd": false
          }
        ]
      },
      "fFamily": "Times New Roman"
    },
    {
      "ch": "O",
      "size": 36,
      "style": "Regular",
      "w": 72.22,
      "data": {
        "shapes": [
          {
            "ty": "gr",
            "it": [
              {
                "ind": 0,
                "ty": "sh",
                "ix": 1,
                "ks": {
                  "a": 0,
                  "k": {
                    "i": [
                      [
                        6.217,
                        -5.762
                      ],
                      [
                        0,
                        -10.514
                      ],
                      [
                        -6.201,
                        -6.477
                      ],
                      [
                        -9.115,
                        0
                      ],
                      [
                        -6.348,
                        6.641
                      ],
                      [
                        0,
                        10.059
                      ],
                      [
                        6.299,
                        6.527
                      ],
                      [
                        8.594,
                        0
                      ]
                    ],
                    "o": [
                      [
                        -7.162,
                        6.641
                      ],
                      [
                        0,
                        10.287
                      ],
                      [
                        6.201,
                        6.478
                      ],
                      [
                        9.016,
                        0
                      ],
                      [
                        6.348,
                        -6.641
                      ],
                      [
                        0,
                        -9.766
                      ],
                      [
                        -6.299,
                        -6.526
                      ],
                      [
                        -8.659,
                        0
                      ]
                    ],
                    "v": [
                      [
                        14.258,
                        -59.082
                      ],
                      [
                        3.516,
                        -33.35
                      ],
                      [
                        12.817,
                        -8.203
                      ],
                      [
                        35.791,
                        1.514
                      ],
                      [
                        58.838,
                        -8.447
                      ],
                      [
                        68.359,
                        -33.496
                      ],
                      [
                        58.911,
                        -57.935
                      ],
                      [
                        36.572,
                        -67.725
                      ]
                    ],
                    "c": true
                  },
                  "ix": 2
                },
                "nm": "O",
                "mn": "ADBE Vector Shape - Group",
                "hd": false
              },
              {
                "ind": 1,
                "ty": "sh",
                "ix": 2,
                "ks": {
                  "a": 0,
                  "k": {
                    "i": [
                      [
                        -3.581,
                        -4.427
                      ],
                      [
                        0,
                        -11.328
                      ],
                      [
                        4.053,
                        -4.85
                      ],
                      [
                        6.217,
                        0
                      ],
                      [
                        3.548,
                        4.427
                      ],
                      [
                        0,
                        10.808
                      ],
                      [
                        -4.46,
                        5.469
                      ],
                      [
                        -5.925,
                        0
                      ]
                    ],
                    "o": [
                      [
                        4.459,
                        5.566
                      ],
                      [
                        0,
                        10.449
                      ],
                      [
                        -4.053,
                        4.851
                      ],
                      [
                        -5.827,
                        0
                      ],
                      [
                        -4.623,
                        -5.827
                      ],
                      [
                        0,
                        -10.547
                      ],
                      [
                        3.58,
                        -4.395
                      ],
                      [
                        6.315,
                        0
                      ]
                    ],
                    "v": [
                      [
                        50.488,
                        -57.52
                      ],
                      [
                        57.178,
                        -32.178
                      ],
                      [
                        51.099,
                        -9.229
                      ],
                      [
                        35.693,
                        -1.953
                      ],
                      [
                        21.631,
                        -8.594
                      ],
                      [
                        14.697,
                        -33.545
                      ],
                      [
                        21.387,
                        -57.568
                      ],
                      [
                        35.645,
                        -64.16
                      ]
                    ],
                    "c": true
                  },
                  "ix": 2
                },
                "nm": "O",
                "mn": "ADBE Vector Shape - Group",
                "hd": false
              }
            ],
            "nm": "O",
            "np": 5,
            "cix": 2,
            "bm": 0,
            "ix": 1,
            "mn": "ADBE Vector Group",
            "hd": false
          }
        ]
      },
      "fFamily": "Times New Roman"
    },
    {
      "ch": "\r",
      "size": 36,
      "style": "Regular",
      "w": 0,
      "fFamily": "Times New Roman"
    },
    {
      "ch": "R",
      "size": 36,
      "style": "Regular",
      "w": 66.7,
      "data": {
        "shapes": [
          {
            "ty": "gr",
            "it": [
              {
                "ind": 0,
                "ty": "sh",
                "ix": 1,
                "ks": {
                  "a": 0,
                  "k": {
                    "i": [
                      [
                        0,
                        0
                      ],
                      [
                        2.246,
                        1.433
                      ],
                      [
                        3.125,
                        4.362
                      ],
                      [
                        0,
                        0
                      ],
                      [
                        -2.654,
                        2.995
                      ],
                      [
                        0,
                        4.07
                      ],
                      [
                        2.327,
                        2.751
                      ],
                      [
                        3.336,
                        1.025
                      ],
                      [
                        7.031,
                        0
                      ],
                      [
                        0,
                        0
                      ],
                      [
                        0,
                        0
                      ],
                      [
                        0,
                        0
                      ],
                      [
                        -1.27,
                        -1.432
                      ],
                      [
                        0,
                        -4.166
                      ],
                      [
                        0,
                        0
                      ],
                      [
                        0.684,
                        -1.009
                      ],
                      [
                        2.799,
                        0
                      ],
                      [
                        0,
                        0
                      ],
                      [
                        0,
                        0
                      ],
                      [
                        0,
                        0
                      ],
                      [
                        0,
                        0
                      ],
                      [
                        0,
                        0
                      ],
                      [
                        1.237,
                        1.433
                      ],
                      [
                        0,
                        4.167
                      ],
                      [
                        0,
                        0
                      ],
                      [
                        -0.488,
                        -0.016
                      ],
                      [
                        -0.423,
                        0
                      ],
                      [
                        -1.66,
                        0.066
                      ],
                      [
                        0,
                        0
                      ],
                      [
                        0,
                        0
                      ]
                    ],
                    "o": [
                      [
                        -3.613,
                        -0.391
                      ],
                      [
                        -2.246,
                        -1.432
                      ],
                      [
                        0,
                        0
                      ],
                      [
                        5.566,
                        -1.237
                      ],
                      [
                        2.653,
                        -2.995
                      ],
                      [
                        0,
                        -3.809
                      ],
                      [
                        -2.328,
                        -2.75
                      ],
                      [
                        -3.337,
                        -1.025
                      ],
                      [
                        0,
                        0
                      ],
                      [
                        0,
                        0
                      ],
                      [
                        0,
                        0
                      ],
                      [
                        2.506,
                        0
                      ],
                      [
                        0.911,
                        1.009
                      ],
                      [
                        0,
                        0
                      ],
                      [
                        0,
                        3.777
                      ],
                      [
                        -1.205,
                        1.823
                      ],
                      [
                        0,
                        0
                      ],
                      [
                        0,
                        0
                      ],
                      [
                        0,
                        0
                      ],
                      [
                        0,
                        0
                      ],
                      [
                        0,
                        0
                      ],
                      [
                        -2.474,
                        0
                      ],
                      [
                        -0.912,
                        -1.009
                      ],
                      [
                        0,
                        0
                      ],
                      [
                        0.52,
                        0.033
                      ],
                      [
                        0.488,
                        0.017
                      ],
                      [
                        1.041,
                        0
                      ],
                      [
                        0,
                        0
                      ],
                      [
                        0,
                        0
                      ],
                      [
                        0,
                        0
                      ]
                    ],
                    "v": [
                      [
                        67.578,
                        -1.807
                      ],
                      [
                        58.789,
                        -4.541
                      ],
                      [
                        50.732,
                        -13.232
                      ],
                      [
                        37.061,
                        -32.227
                      ],
                      [
                        49.39,
                        -38.574
                      ],
                      [
                        53.369,
                        -49.17
                      ],
                      [
                        49.878,
                        -59.009
                      ],
                      [
                        41.382,
                        -64.673
                      ],
                      [
                        25.83,
                        -66.211
                      ],
                      [
                        1.709,
                        -66.211
                      ],
                      [
                        1.709,
                        -64.404
                      ],
                      [
                        4.199,
                        -64.404
                      ],
                      [
                        9.863,
                        -62.256
                      ],
                      [
                        11.23,
                        -54.492
                      ],
                      [
                        11.23,
                        -11.719
                      ],
                      [
                        10.205,
                        -4.541
                      ],
                      [
                        4.199,
                        -1.807
                      ],
                      [
                        1.709,
                        -1.807
                      ],
                      [
                        1.709,
                        0
                      ],
                      [
                        30.078,
                        0
                      ],
                      [
                        30.078,
                        -1.807
                      ],
                      [
                        27.49,
                        -1.807
                      ],
                      [
                        21.924,
                        -3.955
                      ],
                      [
                        20.557,
                        -11.719
                      ],
                      [
                        20.557,
                        -30.957
                      ],
                      [
                        22.07,
                        -30.884
                      ],
                      [
                        23.438,
                        -30.859
                      ],
                      [
                        27.49,
                        -30.957
                      ],
                      [
                        49.902,
                        0
                      ],
                      [
                        67.578,
                        0
                      ]
                    ],
                    "c": true
                  },
                  "ix": 2
                },
                "nm": "R",
                "mn": "ADBE Vector Shape - Group",
                "hd": false
              },
              {
                "ind": 1,
                "ty": "sh",
                "ix": 2,
                "ks": {
                  "a": 0,
                  "k": {
                    "i": [
                      [
                        0,
                        0
                      ],
                      [
                        -1.888,
                        0
                      ],
                      [
                        -2.588,
                        -2.588
                      ],
                      [
                        0,
                        -4.134
                      ],
                      [
                        3.206,
                        -2.734
                      ],
                      [
                        6.315,
                        0
                      ],
                      [
                        0.455,
                        0.017
                      ],
                      [
                        0.618,
                        0
                      ]
                    ],
                    "o": [
                      [
                        3.223,
                        -0.618
                      ],
                      [
                        4.264,
                        0
                      ],
                      [
                        2.588,
                        2.588
                      ],
                      [
                        0,
                        4.232
                      ],
                      [
                        -3.207,
                        2.734
                      ],
                      [
                        -0.293,
                        0
                      ],
                      [
                        -0.456,
                        -0.016
                      ],
                      [
                        0,
                        0
                      ]
                    ],
                    "v": [
                      [
                        20.557,
                        -61.572
                      ],
                      [
                        28.223,
                        -62.5
                      ],
                      [
                        38.501,
                        -58.618
                      ],
                      [
                        42.383,
                        -48.535
                      ],
                      [
                        37.573,
                        -38.086
                      ],
                      [
                        23.291,
                        -33.984
                      ],
                      [
                        22.168,
                        -34.009
                      ],
                      [
                        20.557,
                        -34.033
                      ]
                    ],
                    "c": true
                  },
                  "ix": 2
                },
                "nm": "R",
                "mn": "ADBE Vector Shape - Group",
                "hd": false
              }
            ],
            "nm": "R",
            "np": 5,
            "cix": 2,
            "bm": 0,
            "ix": 1,
            "mn": "ADBE Vector Group",
            "hd": false
          }
        ]
      },
      "fFamily": "Times New Roman"
    },
    {
      "ch": "+",
      "size": 36,
      "style": "Regular",
      "w": 56.4,
      "data": {
        "shapes": [
          {
            "ty": "gr",
            "it": [
              {
                "ind": 0,
                "ty": "sh",
                "ix": 1,
                "ks": {
                  "a": 0,
                  "k": {
                    "i": [
                      [
                        0,
                        0
                      ],
                      [
                        0,
                        0
                      ],
                      [
                        0,
                        0
                      ],
                      [
                        0,
                        0
                      ],
                      [
                        0,
                        0
                      ],
                      [
                        0,
                        0
                      ],
                      [
                        0,
                        0
                      ],
                      [
                        0,
                        0
                      ],
                      [
                        0,
                        0
                      ],
                      [
                        0,
                        0
                      ],
                      [
                        0,
                        0
                      ],
                      [
                        0,
                        0
                      ]
                    ],
                    "o": [
                      [
                        0,
                        0
                      ],
                      [
                        0,
                        0
                      ],
                      [
                        0,
                        0
                      ],
                      [
                        0,
                        0
                      ],
                      [
                        0,
                        0
                      ],
                      [
                        0,
                        0
                      ],
                      [
                        0,
                        0
                      ],
                      [
                        0,
                        0
                      ],
                      [
                        0,
                        0
                      ],
                      [
                        0,
                        0
                      ],
                      [
                        0,
                        0
                      ],
                      [
                        0,
                        0
                      ]
                    ],
                    "v": [
                      [
                        30.029,
                        -6.885
                      ],
                      [
                        30.029,
                        -31.25
                      ],
                      [
                        54.443,
                        -31.25
                      ],
                      [
                        54.443,
                        -35.254
                      ],
                      [
                        30.029,
                        -35.254
                      ],
                      [
                        30.029,
                        -59.521
                      ],
                      [
                        26.123,
                        -59.521
                      ],
                      [
                        26.123,
                        -35.254
                      ],
                      [
                        1.807,
                        -35.254
                      ],
                      [
                        1.807,
                        -31.25
                      ],
                      [
                        26.123,
                        -31.25
                      ],
                      [
                        26.123,
                        -6.885
                      ]
                    ],
                    "c": true
                  },
                  "ix": 2
                },
                "nm": "+",
                "mn": "ADBE Vector Shape - Group",
                "hd": false
              }
            ],
            "nm": "+",
            "np": 3,
            "cix": 2,
            "bm": 0,
            "ix": 1,
            "mn": "ADBE Vector Group",
            "hd": false
          }
        ]
      },
      "fFamily": "Times New Roman"
    }
  ],
  "ddd": 0,
  "fonts": {
    "list": [
      {
        "fName": "TimesNewRomanPSMT",
        "fFamily": "Times New Roman",
        "fStyle": "Regular",
        "ascent": 69.4992065429688
      }
    ]
  },
  "fr": 30,
  "h": 844,
  "ip": 0,
  "layers": [
    {
      "ddd": 0,
      "ind": 1,
      "ty": 2,
      "ty": 2,
      "nm": "Morr Logo.png",
      "cl": "png",
      "refId": "image_0",
      "sr": 1,
      "ks": {
        "o": {
          "a": 0,
          "k": 100,
          "ix": 11
        },
        "r": {
          "a": 0,
          "k": 0,
          "ix": 10
        },
        "p": {
          "a": 0,
          "k": [
            195,
            422,
            0
          ],
          "ix": 2,
          "l": 2
        },
        "a": {
          "a": 0,
          "k": [
            220.5,
            232,
            0
          ],
          "ix": 1,
          "l": 2
        },
        "s": {
          "a": 0,
          "k": [
            15.836,
            15.836,
            100
          ],
          "ix": 6,
          "l": 2
        }
      },
      "ao": 0,
      "ip": 0,
      "op": 90,
      "st": 0,
      "bm": 0
    },
    {
      "ddd": 0,
      "ind": 2,
      "ty": 4,
      "nm": "Inner",
      "sr": 1,
      "ks": {
        "o": {
          "a": 0,
          "k": 100,
          "ix": 11
        },
        "r": {
          "a": 1,
          "k": [
            {
              "i": {
                "x": [
                  0.833
                ],
                "y": [
                  0.833
                ]
              },
              "o": {
                "x": [
                  0.167
                ],
                "y": [
                  0.167
                ]
              },
              "t": 0,
              "s": [
                45
              ]
            },
            {
              "i": {
                "x": [
                  0.833
                ],
                "y": [
                  0.833
                ]
              },
              "o": {
                "x": [
                  0.167
                ],
                "y": [
                  0.167
                ]
              },
              "t": 5,
              "s": [
                45.01
              ]
            },
            {
              "i": {
                "x": [
                  0.833
                ],
                "y": [
                  0.833
                ]
              },
              "o": {
                "x": [
                  0.167
                ],
                "y": [
                  0.167
                ]
              },
              "t": 10,
              "s": [
                90
              ]
            },
            {
              "i": {
                "x": [
                  0.833
                ],
                "y": [
                  0.833
                ]
              },
              "o": {
                "x": [
                  0.167
                ],
                "y": [
                  0.167
                ]
              },
              "t": 15,
              "s": [
                90.01
              ]
            },
            {
              "i": {
                "x": [
                  0.833
                ],
                "y": [
                  0.833
                ]
              },
              "o": {
                "x": [
                  0.167
                ],
                "y": [
                  0.167
                ]
              },
              "t": 20,
              "s": [
                135
              ]
            },
            {
              "i": {
                "x": [
                  0.833
                ],
                "y": [
                  0.833
                ]
              },
              "o": {
                "x": [
                  0.167
                ],
                "y": [
                  0.167
                ]
              },
              "t": 25,
              "s": [
                135.01
              ]
            },
            {
              "i": {
                "x": [
                  0.833
                ],
                "y": [
                  0.833
                ]
              },
              "o": {
                "x": [
                  0.167
                ],
                "y": [
                  0.167
                ]
              },
              "t": 30,
              "s": [
                180
              ]
            },
            {
              "i": {
                "x": [
                  0.833
                ],
                "y": [
                  0.833
                ]
              },
              "o": {
                "x": [
                  0.167
                ],
                "y": [
                  0.167
                ]
              },
              "t": 35,
              "s": [
                180.01
              ]
            },
            {
              "t": 40,
              "s": [
                225
              ]
            }
          ],
          "ix": 10
        },
        "p": {
          "a": 0,
          "k": [
            195,
            422,
            0
          ],
          "ix": 2,
          "l": 2
        },
        "a": {
          "a": 0,
          "k": [
            0,
            0,
            0
          ],
          "ix": 1,
          "l": 2
        },
        "s": {
          "a": 0,
          "k": [
            100,
            100,
            100
          ],
          "ix": 6,
          "l": 2
        }
      },
      "ao": 0,
      "shapes": [
        {
          "ty": "rc",
          "d": 1,
          "s": {
            "a": 0,
            "k": [
              127.94,
              127.94
            ],
            "ix": 2
          },
          "p": {
            "a": 0,
            "k": [
              0,
              0
            ],
            "ix": 3
          },
          "r": {
            "a": 0,
            "k": 25,
            "ix": 4
          },
          "nm": "Rectangle Path 1",
          "mn": "ADBE Vector Shape - Rect",
          "hd": false
        },
        {
          "ty": "fl",
          "c": {
            "a": 0,
            "k": [
              0.985882461071,
              0.985882461071,
              0.985882461071,
              1
            ],
            "ix": 4
          },
          "o": {
            "a": 0,
            "k": 100,
            "ix": 5
          },
          "r": 1,
          "bm": 0,
          "nm": "Fill 1",
          "mn": "ADBE Vector Graphic - Fill",
          "hd": false
        }
      ],
      "ip": 0,
      "op": 92,
      "st": 0,
      "bm": 0
    },
    {
      "ddd": 0,
      "ind": 3,
      "ty": 4,
      "nm": "pointer 12",
      "sr": 1,
      "ks": {
        "o": {
          "a": 0,
          "k": 70,
          "ix": 11
        },
        "r": {
          "a": 0,
          "k": 38.8,
          "ix": 10
        },
        "p": {
          "a": 1,
          "k": [
            {
              "i": {
                "x": 0.833,
                "y": 0.833
              },
              "o": {
                "x": 0.167,
                "y": 0.167
              },
              "t": 85,
              "s": [
                274.036,
                496.8,
                0
              ],
              "to": [
                -15,
                -11,
                0
              ],
              "ti": [
                15,
                11,
                0
              ]
            },
            {
              "t": 89,
              "s": [
                184.036,
                430.8,
                0
              ]
            }
          ],
          "ix": 2,
          "l": 2
        },
        "a": {
          "a": 0,
          "k": [
            0,
            0,
            0
          ],
          "ix": 1,
          "l": 2
        },
        "s": {
          "a": 0,
          "k": [
            34.826,
            7.019,
            100
          ],
          "ix": 6,
          "l": 2
        }
      },
      "ao": 0,
      "shapes": [
        {
          "ty": "rc",
          "d": 1,
          "s": {
            "a": 0,
            "k": [
              100,
              100
            ],
            "ix": 2
          },
          "p": {
            "a": 0,
            "k": [
              0,
              0
            ],
            "ix": 3
          },
          "r": {
            "a": 0,
            "k": 20,
            "ix": 4
          },
          "nm": "Rectangle Path 1",
          "mn": "ADBE Vector Shape - Rect",
          "hd": false
        },
        {
          "ty": "fl",
          "c": {
            "a": 0,
            "k": [
              0.98431378603,
              0.796078503132,
              0.839215755463,
              1
            ],
            "ix": 4
          },
          "o": {
            "a": 0,
            "k": 100,
            "ix": 5
          },
          "r": 1,
          "bm": 0,
          "nm": "Fill 1",
          "mn": "ADBE Vector Graphic - Fill",
          "hd": false
        }
      ],
      "ip": 85,
      "op": 92,
      "st": 0,
      "bm": 0
    },
    {
      "ddd": 0,
      "ind": 4,
      "ty": 4,
      "nm": "pointer 7",
      "sr": 1,
      "ks": {
        "o": {
          "a": 0,
          "k": 70,
          "ix": 11
        },
        "r": {
          "a": 0,
          "k": 38.8,
          "ix": 10
        },
        "p": {
          "a": 1,
          "k": [
            {
              "i": {
                "x": 0.833,
                "y": 0.833
              },
              "o": {
                "x": 0.167,
                "y": 0.167
              },
              "t": 45,
              "s": [
                194.036,
                430.8,
                0
              ],
              "to": [
                13.333,
                11,
                0
              ],
              "ti": [
                -13.333,
                -11,
                0
              ]
            },
            {
              "t": 50,
              "s": [
                274.036,
                496.8,
                0
              ]
            }
          ],
          "ix": 2,
          "l": 2
        },
        "a": {
          "a": 0,
          "k": [
            0,
            0,
            0
          ],
          "ix": 1,
          "l": 2
        },
        "s": {
          "a": 0,
          "k": [
            34.826,
            7.019,
            100
          ],
          "ix": 6,
          "l": 2
        }
      },
      "ao": 0,
      "shapes": [
        {
          "ty": "rc",
          "d": 1,
          "s": {
            "a": 0,
            "k": [
              100,
              100
            ],
            "ix": 2
          },
          "p": {
            "a": 0,
            "k": [
              0,
              0
            ],
            "ix": 3
          },
          "r": {
            "a": 0,
            "k": 20,
            "ix": 4
          },
          "nm": "Rectangle Path 1",
          "mn": "ADBE Vector Shape - Rect",
          "hd": false
        },
        {
          "ty": "fl",
          "c": {
            "a": 0,
            "k": [
              0.98431378603,
              0.796078503132,
              0.839215755463,
              1
            ],
            "ix": 4
          },
          "o": {
            "a": 0,
            "k": 100,
            "ix": 5
          },
          "r": 1,
          "bm": 0,
          "nm": "Fill 1",
          "mn": "ADBE Vector Graphic - Fill",
          "hd": false
        }
      ],
      "ip": 45,
      "op": 86,
      "st": 0,
      "bm": 0
    },
    {
      "ddd": 0,
      "ind": 5,
      "ty": 4,
      "nm": "pointer 11",
      "sr": 1,
      "ks": {
        "o": {
          "a": 0,
          "k": 70,
          "ix": 11
        },
        "r": {
          "a": 0,
          "k": 38.8,
          "ix": 10
        },
        "p": {
          "a": 1,
          "k": [
            {
              "i": {
                "x": 0.833,
                "y": 0.833
              },
              "o": {
                "x": 0.167,
                "y": 0.167
              },
              "t": 85,
              "s": [
                113.8,
                348,
                0
              ],
              "to": [
                12,
                9.333,
                0
              ],
              "ti": [
                -12,
                -9.333,
                0
              ]
            },
            {
              "t": 89,
              "s": [
                185.8,
                404,
                0
              ]
            }
          ],
          "ix": 2,
          "l": 2
        },
        "a": {
          "a": 0,
          "k": [
            0,
            0,
            0
          ],
          "ix": 1,
          "l": 2
        },
        "s": {
          "a": 0,
          "k": [
            34.826,
            7.019,
            100
          ],
          "ix": 6,
          "l": 2
        }
      },
      "ao": 0,
      "shapes": [
        {
          "ty": "rc",
          "d": 1,
          "s": {
            "a": 0,
            "k": [
              100,
              100
            ],
            "ix": 2
          },
          "p": {
            "a": 0,
            "k": [
              0,
              0
            ],
            "ix": 3
          },
          "r": {
            "a": 0,
            "k": 20,
            "ix": 4
          },
          "nm": "Rectangle Path 1",
          "mn": "ADBE Vector Shape - Rect",
          "hd": false
        },
        {
          "ty": "fl",
          "c": {
            "a": 0,
            "k": [
              0.98431378603,
              0.796078503132,
              0.839215755463,
              1
            ],
            "ix": 4
          },
          "o": {
            "a": 0,
            "k": 100,
            "ix": 5
          },
          "r": 1,
          "bm": 0,
          "nm": "Fill 1",
          "mn": "ADBE Vector Graphic - Fill",
          "hd": false
        }
      ],
      "ip": 85,
      "op": 92,
      "st": 0,
      "bm": 0
    },
    {
      "ddd": 0,
      "ind": 6,
      "ty": 4,
      "nm": "pointer 5",
      "sr": 1,
      "ks": {
        "o": {
          "a": 0,
          "k": 70,
          "ix": 11
        },
        "r": {
          "a": 0,
          "k": 38.8,
          "ix": 10
        },
        "p": {
          "a": 1,
          "k": [
            {
              "i": {
                "x": 0.833,
                "y": 0.833
              },
              "o": {
                "x": 0.167,
                "y": 0.167
              },
              "t": 45,
              "s": [
                183.8,
                412,
                0
              ],
              "to": [
                -11.667,
                -10.667,
                0
              ],
              "ti": [
                11.667,
                10.667,
                0
              ]
            },
            {
              "t": 50,
              "s": [
                113.8,
                348,
                0
              ]
            }
          ],
          "ix": 2,
          "l": 2
        },
        "a": {
          "a": 0,
          "k": [
            0,
            0,
            0
          ],
          "ix": 1,
          "l": 2
        },
        "s": {
          "a": 0,
          "k": [
            34.826,
            7.019,
            100
          ],
          "ix": 6,
          "l": 2
        }
      },
      "ao": 0,
      "shapes": [
        {
          "ty": "rc",
          "d": 1,
          "s": {
            "a": 0,
            "k": [
              100,
              100
            ],
            "ix": 2
          },
          "p": {
            "a": 0,
            "k": [
              0,
              0
            ],
            "ix": 3
          },
          "r": {
            "a": 0,
            "k": 20,
            "ix": 4
          },
          "nm": "Rectangle Path 1",
          "mn": "ADBE Vector Shape - Rect",
          "hd": false
        },
        {
          "ty": "fl",
          "c": {
            "a": 0,
            "k": [
              0.98431378603,
              0.796078503132,
              0.839215755463,
              1
            ],
            "ix": 4
          },
          "o": {
            "a": 0,
            "k": 100,
            "ix": 5
          },
          "r": 1,
          "bm": 0,
          "nm": "Fill 1",
          "mn": "ADBE Vector Graphic - Fill",
          "hd": false
        }
      ],
      "ip": 45,
      "op": 86,
      "st": 0,
      "bm": 0
    },
    {
      "ddd": 0,
      "ind": 7,
      "ty": 4,
      "nm": "pointer 10",
      "sr": 1,
      "ks": {
        "o": {
          "a": 0,
          "k": 70,
          "ix": 11
        },
        "r": {
          "a": 0,
          "k": -218.9,
          "ix": 10
        },
        "p": {
          "a": 1,
          "k": [
            {
              "i": {
                "x": 0.833,
                "y": 0.833
              },
              "o": {
                "x": 0.167,
                "y": 0.167
              },
              "t": 85,
              "s": [
                274,
                348,
                0
              ],
              "to": [
                -12,
                10,
                0
              ],
              "ti": [
                12,
                -10,
                0
              ]
            },
            {
              "t": 89,
              "s": [
                202,
                408,
                0
              ]
            }
          ],
          "ix": 2,
          "l": 2
        },
        "a": {
          "a": 0,
          "k": [
            0,
            0,
            0
          ],
          "ix": 1,
          "l": 2
        },
        "s": {
          "a": 0,
          "k": [
            34.519,
            6.665,
            100
          ],
          "ix": 6,
          "l": 2
        }
      },
      "ao": 0,
      "shapes": [
        {
          "ty": "rc",
          "d": 1,
          "s": {
            "a": 0,
            "k": [
              100,
              100
            ],
            "ix": 2
          },
          "p": {
            "a": 0,
            "k": [
              0,
              0
            ],
            "ix": 3
          },
          "r": {
            "a": 0,
            "k": 20,
            "ix": 4
          },
          "nm": "Rectangle Path 1",
          "mn": "ADBE Vector Shape - Rect",
          "hd": false
        },
        {
          "ty": "fl",
          "c": {
            "a": 0,
            "k": [
              0.98431378603,
              0.796078503132,
              0.839215755463,
              1
            ],
            "ix": 4
          },
          "o": {
            "a": 0,
            "k": 100,
            "ix": 5
          },
          "r": 1,
          "bm": 0,
          "nm": "Fill 1",
          "mn": "ADBE Vector Graphic - Fill",
          "hd": false
        }
      ],
      "ip": 85,
      "op": 92,
      "st": 0,
      "bm": 0
    },
    {
      "ddd": 0,
      "ind": 8,
      "ty": 4,
      "nm": "pointer 8",
      "sr": 1,
      "ks": {
        "o": {
          "a": 0,
          "k": 70,
          "ix": 11
        },
        "r": {
          "a": 0,
          "k": -218.9,
          "ix": 10
        },
        "p": {
          "a": 1,
          "k": [
            {
              "i": {
                "x": 0.833,
                "y": 0.833
              },
              "o": {
                "x": 0.167,
                "y": 0.167
              },
              "t": 45,
              "s": [
                198,
                418,
                0
              ],
              "to": [
                12.667,
                -11.667,
                0
              ],
              "ti": [
                -12.667,
                11.667,
                0
              ]
            },
            {
              "t": 50,
              "s": [
                274,
                348,
                0
              ]
            }
          ],
          "ix": 2,
          "l": 2
        },
        "a": {
          "a": 0,
          "k": [
            0,
            0,
            0
          ],
          "ix": 1,
          "l": 2
        },
        "s": {
          "a": 0,
          "k": [
            34.519,
            6.665,
            100
          ],
          "ix": 6,
          "l": 2
        }
      },
      "ao": 0,
      "shapes": [
        {
          "ty": "rc",
          "d": 1,
          "s": {
            "a": 0,
            "k": [
              100,
              100
            ],
            "ix": 2
          },
          "p": {
            "a": 0,
            "k": [
              0,
              0
            ],
            "ix": 3
          },
          "r": {
            "a": 0,
            "k": 20,
            "ix": 4
          },
          "nm": "Rectangle Path 1",
          "mn": "ADBE Vector Shape - Rect",
          "hd": false
        },
        {
          "ty": "fl",
          "c": {
            "a": 0,
            "k": [
              0.98431378603,
              0.796078503132,
              0.839215755463,
              1
            ],
            "ix": 4
          },
          "o": {
            "a": 0,
            "k": 100,
            "ix": 5
          },
          "r": 1,
          "bm": 0,
          "nm": "Fill 1",
          "mn": "ADBE Vector Graphic - Fill",
          "hd": false
        }
      ],
      "ip": 45,
      "op": 86,
      "st": 0,
      "bm": 0
    },
    {
      "ddd": 0,
      "ind": 9,
      "ty": 4,
      "nm": "pointer 9",
      "sr": 1,
      "ks": {
        "o": {
          "a": 0,
          "k": 70,
          "ix": 11
        },
        "r": {
          "a": 0,
          "k": -218.9,
          "ix": 10
        },
        "p": {
          "a": 1,
          "k": [
            {
              "i": {
                "x": 0.833,
                "y": 0.833
              },
              "o": {
                "x": 0.167,
                "y": 0.167
              },
              "t": 85,
              "s": [
                113.791,
                496.833,
                0
              ],
              "to": [
                13.333,
                -10,
                0
              ],
              "ti": [
                -13.333,
                10,
                0
              ]
            },
            {
              "t": 89,
              "s": [
                193.791,
                436.833,
                0
              ]
            }
          ],
          "ix": 2,
          "l": 2
        },
        "a": {
          "a": 0,
          "k": [
            0,
            0,
            0
          ],
          "ix": 1,
          "l": 2
        },
        "s": {
          "a": 0,
          "k": [
            34.519,
            6.665,
            100
          ],
          "ix": 6,
          "l": 2
        }
      },
      "ao": 0,
      "shapes": [
        {
          "ty": "rc",
          "d": 1,
          "s": {
            "a": 0,
            "k": [
              100,
              100
            ],
            "ix": 2
          },
          "p": {
            "a": 0,
            "k": [
              0,
              0
            ],
            "ix": 3
          },
          "r": {
            "a": 0,
            "k": 20,
            "ix": 4
          },
          "nm": "Rectangle Path 1",
          "mn": "ADBE Vector Shape - Rect",
          "hd": false
        },
        {
          "ty": "fl",
          "c": {
            "a": 0,
            "k": [
              0.98431378603,
              0.796078503132,
              0.839215755463,
              1
            ],
            "ix": 4
          },
          "o": {
            "a": 0,
            "k": 100,
            "ix": 5
          },
          "r": 1,
          "bm": 0,
          "nm": "Fill 1",
          "mn": "ADBE Vector Graphic - Fill",
          "hd": false
        }
      ],
      "ip": 85,
      "op": 93,
      "st": 0,
      "bm": 0
    },
    {
      "ddd": 0,
      "ind": 10,
      "ty": 4,
      "nm": "pointer",
      "sr": 1,
      "ks": {
        "o": {
          "a": 0,
          "k": 70,
          "ix": 11
        },
        "r": {
          "a": 0,
          "k": -218.9,
          "ix": 10
        },
        "p": {
          "a": 1,
          "k": [
            {
              "i": {
                "x": 0.833,
                "y": 0.833
              },
              "o": {
                "x": 0.167,
                "y": 0.167
              },
              "t": 45,
              "s": [
                197.791,
                434.833,
                0
              ],
              "to": [
                -14,
                10.333,
                0
              ],
              "ti": [
                14,
                -10.333,
                0
              ]
            },
            {
              "t": 50,
              "s": [
                113.791,
                496.833,
                0
              ]
            }
          ],
          "ix": 2,
          "l": 2
        },
        "a": {
          "a": 0,
          "k": [
            0,
            0,
            0
          ],
          "ix": 1,
          "l": 2
        },
        "s": {
          "a": 0,
          "k": [
            34.519,
            6.665,
            100
          ],
          "ix": 6,
          "l": 2
        }
      },
      "ao": 0,
      "shapes": [
        {
          "ty": "rc",
          "d": 1,
          "s": {
            "a": 0,
            "k": [
              100,
              100
            ],
            "ix": 2
          },
          "p": {
            "a": 0,
            "k": [
              0,
              0
            ],
            "ix": 3
          },
          "r": {
            "a": 0,
            "k": 20,
            "ix": 4
          },
          "nm": "Rectangle Path 1",
          "mn": "ADBE Vector Shape - Rect",
          "hd": false
        },
        {
          "ty": "fl",
          "c": {
            "a": 0,
            "k": [
              0.98431378603,
              0.796078503132,
              0.839215755463,
              1
            ],
            "ix": 4
          },
          "o": {
            "a": 0,
            "k": 100,
            "ix": 5
          },
          "r": 1,
          "bm": 0,
          "nm": "Fill 1",
          "mn": "ADBE Vector Graphic - Fill",
          "hd": false
        }
      ],
      "ip": 45,
      "op": 86,
      "st": 0,
      "bm": 0
    },
    {
      "ddd": 0,
      "ind": 11,
      "ty": 2,
      "nm": "juice.png",
      "cl": "png",
      "refId": "image_1",
      "sr": 1,
      "ks": {
        "o": {
          "a": 0,
          "k": 100,
          "ix": 11
        },
        "r": {
          "a": 0,
          "k": 0,
          "ix": 10
        },
        "p": {
          "a": 1,
          "k": [
            {
              "i": {
                "x": 0.833,
                "y": 0.833
              },
              "o": {
                "x": 0.167,
                "y": 0.167
              },
              "t": 80,
              "s": [
                322.6,
                539,
                0
              ],
              "to": [
                25.233,
                12.667,
                0
              ],
              "ti": [
                -25.233,
                -12.667,
                0
              ]
            },
            {
              "t": 85,
              "s": [
                474,
                615,
                0
              ]
            }
          ],
          "ix": 2,
          "l": 2
        },
        "a": {
          "a": 0,
          "k": [
            242,
            244.5,
            0
          ],
          "ix": 1,
          "l": 2
        },
        "s": {
          "a": 0,
          "k": [
            13.292,
            13.292,
            100
          ],
          "ix": 6,
          "l": 2
        }
      },
      "ao": 0,
      "ip": 80,
      "op": 86,
      "st": 0,
      "bm": 0
    },
    {
      "ddd": 0,
      "ind": 12,
      "ty": 2,
      "nm": "juice.png",
      "cl": "png",
      "refId": "image_1",
      "sr": 1,
      "ks": {
        "o": {
          "a": 0,
          "k": 100,
          "ix": 11
        },
        "r": {
          "a": 0,
          "k": 0,
          "ix": 10
        },
        "p": {
          "a": 1,
          "k": [
            {
              "i": {
                "x": 0.833,
                "y": 0.833
              },
              "o": {
                "x": 0.167,
                "y": 0.167
              },
              "t": 50,
              "s": [
                474.6,
                615,
                0
              ],
              "to": [
                -25.333,
                -12.667,
                0
              ],
              "ti": [
                25.333,
                12.667,
                0
              ]
            },
            {
              "t": 55,
              "s": [
                322.6,
                539,
                0
              ]
            }
          ],
          "ix": 2,
          "l": 2
        },
        "a": {
          "a": 0,
          "k": [
            242,
            244.5,
            0
          ],
          "ix": 1,
          "l": 2
        },
        "s": {
          "a": 0,
          "k": [
            13.292,
            13.292,
            100
          ],
          "ix": 6,
          "l": 2
        }
      },
      "ao": 0,
      "ip": 50,
      "op": 80,
      "st": 0,
      "bm": 0
    },
    {
      "ddd": 0,
      "ind": 13,
      "ty": 2,
      "nm": "milk.png",
      "cl": "png",
      "refId": "image_2",
      "sr": 1,
      "ks": {
        "o": {
          "a": 0,
          "k": 100,
          "ix": 11
        },
        "r": {
          "a": 0,
          "k": 0,
          "ix": 10
        },
        "p": {
          "a": 1,
          "k": [
            {
              "i": {
                "x": 0.833,
                "y": 0.833
              },
              "o": {
                "x": 0.167,
                "y": 0.167
              },
              "t": 80,
              "s": [
                64.9,
                539,
                0
              ],
              "to": [
                -21.333,
                12.667,
                0
              ],
              "ti": [
                21.333,
                -12.667,
                0
              ]
            },
            {
              "t": 85,
              "s": [
                -63.1,
                615,
                0
              ]
            }
          ],
          "ix": 2,
          "l": 2
        },
        "a": {
          "a": 0,
          "k": [
            240.5,
            244,
            0
          ],
          "ix": 1,
          "l": 2
        },
        "s": {
          "a": 0,
          "k": [
            13.055,
            13.055,
            100
          ],
          "ix": 6,
          "l": 2
        }
      },
      "ao": 0,
      "ip": 80,
      "op": 86,
      "st": 0,
      "bm": 0
    },
    {
      "ddd": 0,
      "ind": 14,
      "ty": 2,
      "nm": "milk.png",
      "cl": "png",
      "refId": "image_2",
      "sr": 1,
      "ks": {
        "o": {
          "a": 0,
          "k": 100,
          "ix": 11
        },
        "r": {
          "a": 0,
          "k": 0,
          "ix": 10
        },
        "p": {
          "a": 1,
          "k": [
            {
              "i": {
                "x": 0.833,
                "y": 0.833
              },
              "o": {
                "x": 0.167,
                "y": 0.167
              },
              "t": 50,
              "s": [
                -63.062,
                615,
                0
              ],
              "to": [
                21.327,
                -12.667,
                0
              ],
              "ti": [
                -21.327,
                12.667,
                0
              ]
            },
            {
              "t": 55,
              "s": [
                64.9,
                539,
                0
              ]
            }
          ],
          "ix": 2,
          "l": 2
        },
        "a": {
          "a": 0,
          "k": [
            240.5,
            244,
            0
          ],
          "ix": 1,
          "l": 2
        },
        "s": {
          "a": 0,
          "k": [
            13.055,
            13.055,
            100
          ],
          "ix": 6,
          "l": 2
        }
      },
      "ao": 0,
      "ip": 50,
      "op": 80,
      "st": 0,
      "bm": 0
    },
    {
      "ddd": 0,
      "ind": 15,
      "ty": 2,
      "nm": "burger.png",
      "cl": "png",
      "refId": "image_3",
      "sr": 1,
      "ks": {
        "o": {
          "a": 0,
          "k": 100,
          "ix": 11
        },
        "r": {
          "a": 0,
          "k": 0,
          "ix": 10
        },
        "p": {
          "a": 1,
          "k": [
            {
              "i": {
                "x": 0.833,
                "y": 0.833
              },
              "o": {
                "x": 0.167,
                "y": 0.167
              },
              "t": 80,
              "s": [
                322.6,
                299,
                0
              ],
              "to": [
                25.4,
                -19.667,
                0
              ],
              "ti": [
                -25.4,
                19.667,
                0
              ]
            },
            {
              "t": 85,
              "s": [
                475,
                181,
                0
              ]
            }
          ],
          "ix": 2,
          "l": 2
        },
        "a": {
          "a": 0,
          "k": [
            282.5,
            246.5,
            0
          ],
          "ix": 1,
          "l": 2
        },
        "s": {
          "a": 0,
          "k": [
            10.884,
            9.969,
            100
          ],
          "ix": 6,
          "l": 2
        }
      },
      "ao": 0,
      "ip": 80,
      "op": 86,
      "st": 5,
      "bm": 0
    },
    {
      "ddd": 0,
      "ind": 16,
      "ty": 2,
      "nm": "burger.png",
      "cl": "png",
      "refId": "image_3",
      "sr": 1,
      "ks": {
        "o": {
          "a": 0,
          "k": 100,
          "ix": 11
        },
        "r": {
          "a": 0,
          "k": 0,
          "ix": 10
        },
        "p": {
          "a": 1,
          "k": [
            {
              "i": {
                "x": 0.833,
                "y": 0.833
              },
              "o": {
                "x": 0.167,
                "y": 0.167
              },
              "t": 50,
              "s": [
                475.779,
                181,
                0
              ],
              "to": [
                -25.53,
                19.667,
                0
              ],
              "ti": [
                25.53,
                -19.667,
                0
              ]
            },
            {
              "t": 55,
              "s": [
                322.6,
                299,
                0
              ]
            }
          ],
          "ix": 2,
          "l": 2
        },
        "a": {
          "a": 0,
          "k": [
            282.5,
            246.5,
            0
          ],
          "ix": 1,
          "l": 2
        },
        "s": {
          "a": 0,
          "k": [
            10.884,
            9.969,
            100
          ],
          "ix": 6,
          "l": 2
        }
      },
      "ao": 0,
      "ip": 50,
      "op": 80,
      "st": 5,
      "bm": 0
    },
    {
      "ddd": 0,
      "ind": 17,
      "ty": 2,
      "nm": "Untitled-3.png",
      "cl": "png",
      "refId": "image_4",
      "sr": 1,
      "ks": {
        "o": {
          "a": 0,
          "k": 100,
          "ix": 11
        },
        "r": {
          "a": 0,
          "k": 0,
          "ix": 10
        },
        "p": {
          "a": 1,
          "k": [
            {
              "i": {
                "x": 0.833,
                "y": 0.833
              },
              "o": {
                "x": 0.167,
                "y": 0.167
              },
              "t": 80,
              "s": [
                64.9,
                299,
                0
              ],
              "to": [
                -23.833,
                -19.667,
                0
              ],
              "ti": [
                23.833,
                19.667,
                0
              ]
            },
            {
              "t": 85,
              "s": [
                -78.1,
                181,
                0
              ]
            }
          ],
          "ix": 2,
          "l": 2
        },
        "a": {
          "a": 0,
          "k": [
            245,
            185,
            0
          ],
          "ix": 1,
          "l": 2
        },
        "s": {
          "a": 0,
          "k": [
            12.432,
            12.432,
            100
          ],
          "ix": 6,
          "l": 2
        }
      },
      "ao": 0,
      "ip": 80,
      "op": 86,
      "st": 0,
      "bm": 0
    },
    {
      "ddd": 0,
      "ind": 18,
      "ty": 2,
      "nm": "Untitled-3.png",
      "cl": "png",
      "refId": "image_4",
      "sr": 1,
      "ks": {
        "o": {
          "a": 0,
          "k": 100,
          "ix": 11
        },
        "r": {
          "a": 0,
          "k": 0,
          "ix": 10
        },
        "p": {
          "a": 1,
          "k": [
            {
              "i": {
                "x": 0.833,
                "y": 0.833
              },
              "o": {
                "x": 0.167,
                "y": 0.167
              },
              "t": 50,
              "s": [
                -78.1,
                181,
                0
              ],
              "to": [
                23.833,
                19.667,
                0
              ],
              "ti": [
                -23.833,
                -19.667,
                0
              ]
            },
            {
              "t": 55,
              "s": [
                64.9,
                299,
                0
              ]
            }
          ],
          "ix": 2,
          "l": 2
        },
        "a": {
          "a": 0,
          "k": [
            245,
            185,
            0
          ],
          "ix": 1,
          "l": 2
        },
        "s": {
          "a": 0,
          "k": [
            12.432,
            12.432,
            100
          ],
          "ix": 6,
          "l": 2
        }
      },
      "ao": 0,
      "ip": 50,
      "op": 80,
      "st": 0,
      "bm": 0
    },
    {
      "ddd": 0,
      "ind": 19,
      "ty": 5,
      "nm": "MO RR+",
      "sr": 1,
      "ks": {
        "o": {
          "a": 0,
          "k": 100,
          "ix": 11
        },
        "r": {
          "a": 0,
          "k": 0,
          "ix": 10
        },
        "p": {
          "a": 0,
          "k": [
            166,
            420,
            0
          ],
          "ix": 2,
          "l": 2
        },
        "a": {
          "a": 0,
          "k": [
            0,
            0,
            0
          ],
          "ix": 1,
          "l": 2
        },
        "s": {
          "a": 0,
          "k": [
            100,
            100,
            100
          ],
          "ix": 6,
          "l": 2
        }
      },
      "ao": 0,
      "t": {
        "d": {
          "k": [
            {
              "s": {
                "s": 36,
                "f": "TimesNewRomanPSMT",
                "t": "MO\rRR+",
                "j": 0,
                "tr": 0,
                "lh": 43.2000007629395,
                "ls": 0,
                "fc": [
                  0.922,
                  0.922,
                  0.922
                ]
              },
              "t": 0
            }
          ]
        },
        "p": {},
        "m": {
          "g": 1,
          "a": {
            "a": 0,
            "k": [
              0,
              0
            ],
            "ix": 2
          }
        },
        "a": [
          {
            "nm": "Animator 1",
            "s": {
              "t": 0,
              "xe": {
                "a": 0,
                "k": 0,
                "ix": 7
              },
              "ne": {
                "a": 0,
                "k": 0,
                "ix": 8
              },
              "a": {
                "a": 0,
                "k": 100,
                "ix": 4
              },
              "b": 1,
              "rn": 0,
              "sh": 1,
              "r": 1
            },
            "a": {
              "fc": {
                "a": 0,
                "k": [
                  0.778823554516,
                  0.18386349082,
                  0.18386349082,
                  1
                ],
                "ix": 12
              }
            }
          }
        ]
      },
      "ip": 0,
      "op": 90,
      "st": 0,
      "bm": 0
    },
    {
      "ddd": 0,
      "ind": 20,
      "ty": 4,
      "nm": "Shape Layer 1",
      "sr": 1,
      "ks": {
        "o": {
          "a": 0,
          "k": 100,
          "ix": 11
        },
        "r": {
          "a": 1,
          "k": [
            {
              "i": {
                "x": [
                  0.833
                ],
                "y": [
                  0.833
                ]
              },
              "o": {
                "x": [
                  0.167
                ],
                "y": [
                  0.167
                ]
              },
              "t": 0,
              "s": [
                45
              ]
            },
            {
              "i": {
                "x": [
                  0.833
                ],
                "y": [
                  0.833
                ]
              },
              "o": {
                "x": [
                  0.167
                ],
                "y": [
                  0.167
                ]
              },
              "t": 5,
              "s": [
                45.01
              ]
            },
            {
              "i": {
                "x": [
                  0.833
                ],
                "y": [
                  0.833
                ]
              },
              "o": {
                "x": [
                  0.167
                ],
                "y": [
                  0.167
                ]
              },
              "t": 10,
              "s": [
                0
              ]
            },
            {
              "i": {
                "x": [
                  0.833
                ],
                "y": [
                  0.833
                ]
              },
              "o": {
                "x": [
                  0.167
                ],
                "y": [
                  0.167
                ]
              },
              "t": 15,
              "s": [
                0.01
              ]
            },
            {
              "i": {
                "x": [
                  0.833
                ],
                "y": [
                  0.833
                ]
              },
              "o": {
                "x": [
                  0.167
                ],
                "y": [
                  0.167
                ]
              },
              "t": 20,
              "s": [
                -45
              ]
            },
            {
              "i": {
                "x": [
                  0.833
                ],
                "y": [
                  0.833
                ]
              },
              "o": {
                "x": [
                  0.167
                ],
                "y": [
                  0.167
                ]
              },
              "t": 25,
              "s": [
                -45.01
              ]
            },
            {
              "i": {
                "x": [
                  0.833
                ],
                "y": [
                  0.833
                ]
              },
              "o": {
                "x": [
                  0.167
                ],
                "y": [
                  0.167
                ]
              },
              "t": 30,
              "s": [
                -90
              ]
            },
            {
              "i": {
                "x": [
                  0.833
                ],
                "y": [
                  0.833
                ]
              },
              "o": {
                "x": [
                  0.167
                ],
                "y": [
                  0.167
                ]
              },
              "t": 35,
              "s": [
                -90.01
              ]
            },
            {
              "t": 40,
              "s": [
                -135
              ]
            }
          ],
          "ix": 10
        },
        "p": {
          "a": 0,
          "k": [
            195,
            422,
            0
          ],
          "ix": 2,
          "l": 2
        },
        "a": {
          "a": 0,
          "k": [
            0,
            0,
            0
          ],
          "ix": 1,
          "l": 2
        },
        "s": {
          "a": 0,
          "k": [
            100,
            100,
            100
          ],
          "ix": 6,
          "l": 2
        }
      },
      "ao": 0,
      "shapes": [
        {
          "ty": "rc",
          "d": 1,
          "s": {
            "a": 0,
            "k": [
              160,
              160
            ],
            "ix": 2
          },
          "p": {
            "a": 0,
            "k": [
              0,
              0
            ],
            "ix": 3
          },
          "r": {
            "a": 0,
            "k": 25,
            "ix": 4
          },
          "nm": "Rectangle Path 1",
          "mn": "ADBE Vector Shape - Rect",
          "hd": false
        },
        {
          "ty": "fl",
          "c": {
            "a": 0,
            "k": [
              0.97960793972,
              0.950411856174,
              0.950411856174,
              1
            ],
            "ix": 4
          },
          "o": {
            "a": 0,
            "k": 30,
            "ix": 5
          },
          "r": 1,
          "bm": 0,
          "nm": "Fill 1",
          "mn": "ADBE Vector Graphic - Fill",
          "hd": false
        }
      ],
      "ip": 0,
      "op": 90,
      "st": 0,
      "bm": 0
    }
  ],
  "markers": [],
  "nm": "Morr",
  "op": 90,
  "v": "5.7.4",
  "w": 390
}